LICENSE
MANIFEST.in
README.md
setup.py
e_drone_nightly/__init__.py
e_drone_nightly/__main__.py
e_drone_nightly/crc.py
e_drone_nightly/drone.py
e_drone_nightly/protocol.py
e_drone_nightly/receiver.py
e_drone_nightly/storage.py
e_drone_nightly/system.py
e_drone_nightly/update.py
e_drone_nightly.egg-info/PKG-INFO
e_drone_nightly.egg-info/SOURCES.txt
e_drone_nightly.egg-info/dependency_links.txt
e_drone_nightly.egg-info/requires.txt
e_drone_nightly.egg-info/top_level.txt
e_drone_nightly/tools/__init__.py
e_drone_nightly/tools/parser.py
e_drone_nightly/tools/update.py