Metadata-Version: 2.1
Name: e-drone-nightly
Version: 0.1.37
Summary: Library for BYROBOT Drones.
Home-page: http://www.byrobot.co.kr
Author: BYROBOT
Author-email: dev@byrobot.co.kr
License: UNKNOWN
Platform: UNKNOWN
